ez_setup.py
runtests.py
setup.py
unittest.cfg
loggrok/__init__.py
loggrok/actions.py
loggrok/log.py
loggrok/parse.py
loggrok.egg-info/PKG-INFO
loggrok.egg-info/SOURCES.txt
loggrok.egg-info/dependency_links.txt
loggrok.egg-info/requires.txt
loggrok.egg-info/top_level.txt
test/__init__.py
test/loggrok-actions-level.txt
test/loggrok-actions-messageCategory.txt
test/loggrok-log-LogEntry.txt
test/loggrok-log-LogHeader.txt
test/loggrok-log-LogHeader_alternate_parser.txt
test/loggrok-log-LogStream-entry-default.txt
test/loggrok-log-RollingIndexLogStream-basic.txt
test/loggrok-log-RollingIndexLogStream-cutTimestamp.txt
test/loggrok-log-RollingIndexLogStream2-basic.txt
test/data/test-actions.log
test/data/test-basic.log
test/data/test-entry.log
test/data/cuttstamp/test.0.log
test/data/cuttstamp/test.log
test/data/rolling-index/test.0.log
test/data/rolling-index/test.1.log
test/data/rolling-index/test.10.log
test/data/rolling-index/test.log
test/data/rolling-index2/test.log
test/data/rolling-index2/test.log.1
test/data/rolling-index2/test.log.10
test/data/rolling-index2/test.log.2
