Metadata-Version: 1.0
Name: loggrok
Version: 0.2.1
Summary: Simple log analysis library
Home-page: http://xix.python-hosting.com/#loggrok
Author: Drew Smathers
Author-email: drew dot smathers at gmail dot com
License: MIT License
Platform: UNKNOWN
Classifier: Development Status :: 3 - Alpha
Classifier: License :: OSI Approved :: MIT License
Classifier: Operating System :: MacOS :: MacOS X
Classifier: Operating System :: Microsoft :: Windows
Classifier: Operating System :: POSIX
Classifier: Environment :: Console
Classifier: Programming Language :: Python
Classifier: Intended Audience :: Developers
Classifier: Topic :: Utilities
